py_snake-0.0.2.dist-info/METADATA
py_snake-0.0.2.dist-info/RECORD
py_snake-0.0.2.dist-info/WHEEL
py_snake-0.0.2.dist-info/entry_points.txt
py_snake-0.0.2.dist-info/top_level.txt
snake/__init__.py
snake/common.py
snake/compat.py
snake/config.py
snake/controller.py
snake/engine.py
snake/game.py
snake/input.py
snake/kbhit.py
snake/model.py
snake/run.py
snake/snake.py
snake/snake2.py
snake/view.py
