Metadata-Version: 2.1
Name: py-snake
Version: 0.0.2
Summary: CLI Snake game.
Home-page: https://github.com/jakehadar/py-snake
Author: Jake Hadar
Author-email: jakehadar.dev@gmail.com
License: UNKNOWN
Keywords: snake game python cli command line
Platform: UNKNOWN
Classifier: Environment :: Console
Classifier: Intended Audience :: End Users/Desktop
Classifier: Natural Language :: English
Classifier: Operating System :: POSIX
Classifier: Programming Language :: Python :: 2.7
Classifier: Programming Language :: Python :: 3.6
Classifier: Topic :: Games/Entertainment :: Arcade
Classifier: License :: OSI Approved :: MIT License
Classifier: Natural Language :: English
Classifier: Programming Language :: Python
Requires-Python: >=2.7
